{
  "indexes": [
    {
      "collectionGroup": "notifications",
      "queryScope": "COLLECTION",
      "fields": [
        {
          "fieldPath": "userId",
          "order": "ASCENDING"
        },
        {
          "fieldPath": "isRead",
          "order": "ASCENDING"
        },
        {
          "fieldPath": "timestamp",
          "order": "DESCENDING"
        }
      ]
    },
    {
      "collectionGroup": "games",
      "queryScope": "COLLECTION",
      "fields": [
        {
          "fieldPath": "userId",
          "order": "ASCENDING"
        },
        {
          "fieldPath": "timestamp",
          "order": "DESCENDING"
        }
      ]
    },
    {
      "collectionGroup": "games",
      "queryScope": "COLLECTION",
      "fields": [
        {
          "fieldPath": "userId",
          "order": "ASCENDING"
        },
        {
          "fieldPath": "player1",
          "order": "ASCENDING"
        },
        {
          "fieldPath": "timestamp",
          "order": "DESCENDING"
        }
      ]
    },
    {
      "collectionGroup": "games",
      "queryScope": "COLLECTION",
      "fields": [
        {
          "fieldPath": "userId",
          "order": "ASCENDING"
        },
        {
          "fieldPath": "player2",
          "order": "ASCENDING"
        },
        {
          "fieldPath": "timestamp",
          "order": "DESCENDING"
        }
      ]
    },
    {
      "collectionGroup": "players",
      "queryScope": "COLLECTION",
      "fields": [
        {
          "fieldPath": "userId",
          "order": "ASCENDING"
        },
        {
          "fieldPath": "createdAt",
          "order": "DESCENDING"
        }
      ]
    },
    {
      "collectionGroup": "tournaments",
      "queryScope": "COLLECTION",
      "fields": [
        {
          "fieldPath": "category",
          "order": "ASCENDING"
        },
        {
          "fieldPath": "createdAt",
          "order": "DESCENDING"
        }
      ]
    },
    {
      "collectionGroup": "tournaments",
      "queryScope": "COLLECTION",
      "fields": [
        {
          "fieldPath": "category",
          "order": "ASCENDING"
        },
        {
          "fieldPath": "participants",
          "arrayConfig": "CONTAINS"
        },
        {
          "fieldPath": "createdAt",
          "order": "DESCENDING"
        }
      ]
    },
    {
      "collectionGroup": "tournaments",
      "queryScope": "COLLECTION",
      "fields": [
        {
          "fieldPath": "category",
          "order": "ASCENDING"
        },
        {
          "fieldPath": "createdBy",
          "order": "ASCENDING"
        },
        {
          "fieldPath": "createdAt",
          "order": "DESCENDING"
        }
      ]
    },
    {
      "collectionGroup": "tournaments",
      "queryScope": "COLLECTION",
      "fields": [
        {
          "fieldPath": "participants",
          "arrayConfig": "CONTAINS"
        },
        {
          "fieldPath": "createdAt",
          "order": "DESCENDING"
        }
      ]
    },
    {
      "collectionGroup": "tournament_invitations",
      "queryScope": "COLLECTION",
      "fields": [
        {
          "fieldPath": "toUserId",
          "order": "ASCENDING"
        },
        {
          "fieldPath": "status",
          "order": "ASCENDING"
        },
        {
          "fieldPath": "createdAt",
          "order": "DESCENDING"
        }
      ]
    },
    {
      "collectionGroup": "scheduled_notifications",
      "queryScope": "COLLECTION",
      "fields": [
        {
          "fieldPath": "processed",
          "order": "ASCENDING"
        },
        {
          "fieldPath": "scheduledTime",
          "order": "ASCENDING"
        }
      ]
    }
  ],
  "fieldOverrides": []
} 